umiche/__init__.py
umiche/bam/Build.py
umiche/bam/Bundle.py
umiche/bam/Reader.py
umiche/bam/Relation.py
umiche/bam/Writer.py
umiche/bam/__init__.py
umiche/dedup.py
umiche/deduplicate/Gadgetry.py
umiche/deduplicate/Gene.py
umiche/deduplicate/MultiPos.py
umiche/deduplicate/OnePos.py
umiche/deduplicate/SingleCell.py
umiche/deduplicate/TMR.py
umiche/deduplicate/Tabulate.py
umiche/deduplicate/__init__.py
umiche/deduplicate/dimer/SelfHealing.py
umiche/deduplicate/dimer/Shakeup.py
umiche/deduplicate/dimer/__init__.py
umiche/deduplicate/heterogeneity/Trace.py
umiche/deduplicate/heterogeneity/__init__.py
umiche/deduplicate/io/Stat.py
umiche/deduplicate/io/__init__.py
umiche/deduplicate/method/Adjacency.py
umiche/deduplicate/method/Cluster.py
umiche/deduplicate/method/Clustering.py
umiche/deduplicate/method/Directional.py
umiche/deduplicate/method/MarkovClustering.py
umiche/deduplicate/method/ReformKit.py
umiche/deduplicate/method/__init__.py
umiche/deduplicate/method/trimer/Collapse.py
umiche/deduplicate/method/trimer/MajorityVote.py
umiche/deduplicate/method/trimer/SetCover.py
umiche/deduplicate/method/trimer/__init__.py
umiche/deduplicate/pipeline/Heterogeneity.py
umiche/deduplicate/pipeline/Standard.py
umiche/deduplicate/pipeline/UMIBasic.py
umiche/deduplicate/pipeline/UMISingleCell.py
umiche/deduplicate/pipeline/__init__.py
umiche/deduplicate/trimer/SelfHealing.py
umiche/deduplicate/trimer/Shakeup.py
umiche/deduplicate/trimer/__init__.py
umiche/deepconvcvae/CondiConvVAE.py
umiche/deepconvcvae/Extreme.py
umiche/deepconvcvae/PlotTresor.py
umiche/deepconvcvae/PlotUMIche.py
umiche/deepconvcvae/PlotmclUMI.py
umiche/deepconvcvae/Preprocess.py
umiche/deepconvcvae/Simulate.py
umiche/deepconvcvae/Train.py
umiche/deepconvcvae/__init__.py
umiche/deepconvcvae/boxplot/GCMat.py
umiche/deepconvcvae/boxplot/Style.py
umiche/deepconvcvae/boxplot/__init__.py
umiche/deepconvcvae/cv/Split.py
umiche/deepconvcvae/cv/Summary.py
umiche/deepconvcvae/cv/__init__.py
umiche-0.1.5.dist-info/LICENSE
umiche-0.1.5.dist-info/METADATA
umiche-0.1.5.dist-info/WHEEL
umiche-0.1.5.dist-info/RECORD
