Metadata-Version: 2.3
Name: umiche
Version: 0.1.5
Summary: 
Author: Jianfeng Sun
Author-email: jianfeng.sunmt@gmail.com
Requires-Python: >=3.11,<4.0
Classifier: Programming Language :: Python :: 3
Classifier: Programming Language :: Python :: 3.11
Classifier: Programming Language :: Python :: 3.12
Classifier: Programming Language :: Python :: 3.13
Requires-Dist: biopython (>=1.84,<2.0)
Requires-Dist: markov-clustering
Requires-Dist: matplotlib (>=3.9.1,<4.0.0)
Requires-Dist: networkx (>=3.3,<4.0)
Requires-Dist: numpy (>=2.0.1,<3.0.0)
Requires-Dist: pandas (>=2.2.2,<3.0.0)
Requires-Dist: pyfastx (>=2.1.0,<3.0.0)
Requires-Dist: pyfiglet (==0.8.post1)
Requires-Dist: pyyaml (>=6.0.1,<7.0.0)
Requires-Dist: scikit-learn (>=1.5.1,<2.0.0)
Requires-Dist: scipy (>=1.14.0,<2.0.0)
Requires-Dist: seaborn (>=0.13.2,<0.14.0)
